[
  {
    "game_id": "401812722",
    "date": "2025-10-15",
    "league": "NBA",
    "home_team": "CHA",
    "away_team": "MEM",
    "home_team_full": "Charlotte Hornets",
    "away_team_full": "Memphis Grizzlies",
    "home_score": 145,
    "away_score": 116,
    "status": "final",
    "half_scores": {
      "H1": {
        "home": 37,
        "away": 30
      },
      "H2": {
        "home": 29,
        "away": 27
      },
      "OT1": {
        "home": 45,
        "away": 28
      },
      "OT2": {
        "home": 34,
        "away": 31
      }
    },
    "quarter_scores": {},
    "source": "NBA",
    "fetched_at": "2026-01-09T16:05:55.693370"
  },
  {
    "game_id": "401812723",
    "date": "2025-10-15",
    "league": "NBA",
    "home_team": "BOS",
    "away_team": "TOR",
    "home_team_full": "Boston Celtics",
    "away_team_full": "Toronto Raptors",
    "home_score": 110,
    "away_score": 108,
    "status": "final",
    "half_scores": {
      "H1": {
        "home": 30,
        "away": 25
      },
      "H2": {
        "home": 22,
        "away": 25
      },
      "OT1": {
        "home": 27,
        "away": 25
      },
      "OT2": {
        "home": 31,
        "away": 33
      }
    },
    "quarter_scores": {},
    "source": "NBA",
    "fetched_at": "2026-01-09T16:05:55.693370"
  },
  {
    "game_id": "401812725",
    "date": "2025-10-15",
    "league": "NBA",
    "home_team": "SAC",
    "away_team": "LAC",
    "home_team_full": "Sacramento Kings",
    "away_team_full": "LA Clippers",
    "home_score": 91,
    "away_score": 109,
    "status": "final",
    "half_scores": {
      "H1": {
        "home": 18,
        "away": 26
      },
      "H2": {
        "home": 22,
        "away": 34
      },
      "OT1": {
        "home": 21,
        "away": 30
      },
      "OT2": {
        "home": 30,
        "away": 19
      }
    },
    "quarter_scores": {},
    "source": "NBA",
    "fetched_at": "2026-01-09T16:05:55.693370"
  },
  {
    "game_id": "401812724",
    "date": "2025-10-15",
    "league": "NBA",
    "home_team": "LAL",
    "away_team": "DAL",
    "home_team_full": "Los Angeles Lakers",
    "away_team_full": "Dallas Mavericks",
    "home_score": 94,
    "away_score": 121,
    "status": "final",
    "half_scores": {
      "H1": {
        "home": 36,
        "away": 32
      },
      "H2": {
        "home": 30,
        "away": 21
      },
      "OT1": {
        "home": 20,
        "away": 31
      },
      "OT2": {
        "home": 8,
        "away": 37
      }
    },
    "quarter_scores": {},
    "source": "NBA",
    "fetched_at": "2026-01-09T16:05:55.693370"
  }
]