[
  {
    "game_id": 16412,
    "date": "2026-01-02",
    "league": "NCAAF",
    "home_team": "CIN",
    "away_team": "NAVY",
    "home_team_full": "Cincinnati Bearcats",
    "away_team_full": "Navy Midshipmen",
    "home_score": 13,
    "away_score": 35,
    "status": "final",
    "half_scores": {},
    "quarter_scores": {
      "Q1": {
        "home": 0,
        "away": 7
      },
      "Q2": {
        "home": 7,
        "away": 7
      },
      "Q3": {
        "home": 0,
        "away": 7
      },
      "Q4": {
        "home": 6,
        "away": 14
      }
    },
    "source": "NCAAF",
    "fetched_at": "2026-01-09T16:47:00.567728"
  },
  {
    "game_id": 16428,
    "date": "2026-01-02",
    "league": "NCAAF",
    "home_team": "TXST",
    "away_team": "RICE",
    "home_team_full": "Texas State Bobcats",
    "away_team_full": "Rice Owls",
    "home_score": 41,
    "away_score": 10,
    "status": "final",
    "half_scores": {},
    "quarter_scores": {
      "Q1": {
        "home": 0,
        "away": 0
      },
      "Q2": {
        "home": 10,
        "away": 7
      },
      "Q3": {
        "home": 17,
        "away": 0
      },
      "Q4": {
        "home": 14,
        "away": 3
      }
    },
    "source": "NCAAF",
    "fetched_at": "2026-01-09T16:47:00.567728"
  },
  {
    "game_id": 16434,
    "date": "2026-01-02",
    "league": "NCAAF",
    "home_team": "SMU",
    "away_team": "ARZ",
    "home_team_full": "SMU Mustangs",
    "away_team_full": "Arizona Wildcats",
    "home_score": 24,
    "away_score": 19,
    "status": "final",
    "half_scores": {},
    "quarter_scores": {
      "Q1": {
        "home": 14,
        "away": 0
      },
      "Q2": {
        "home": 10,
        "away": 0
      },
      "Q3": {
        "home": 0,
        "away": 6
      },
      "Q4": {
        "home": 0,
        "away": 13
      }
    },
    "source": "NCAAF",
    "fetched_at": "2026-01-09T16:47:00.567728"
  },
  {
    "game_id": 16435,
    "date": "2026-01-02",
    "league": "NCAAF",
    "home_team": "MSPST",
    "away_team": "WAKE",
    "home_team_full": "Mississippi State Bulldogs",
    "away_team_full": "Wake Forest Demon Deacons",
    "home_score": 29,
    "away_score": 43,
    "status": "final",
    "half_scores": {},
    "quarter_scores": {
      "Q1": {
        "home": 6,
        "away": 15
      },
      "Q2": {
        "home": 3,
        "away": 0
      },
      "Q3": {
        "home": 11,
        "away": 15
      },
      "Q4": {
        "home": 9,
        "away": 13
      }
    },
    "source": "NCAAF",
    "fetched_at": "2026-01-09T16:47:00.567728"
  }
]